egse/tempcontrol/keithley/__init__.py
egse/tempcontrol/keithley/daq6510.py
egse/tempcontrol/keithley/daq6510.yaml
egse/tempcontrol/keithley/daq6510_cs.py
egse/tempcontrol/keithley/daq6510_devif.py
egse/tempcontrol/keithley/daq6510_protocol.py
keithley_tempcontrol-2025.0.9.dist-info/METADATA
keithley_tempcontrol-2025.0.9.dist-info/WHEEL
keithley_tempcontrol-2025.0.9.dist-info/entry_points.txt
keithley_tempcontrol-2025.0.9.dist-info/RECORD
