Metadata-Version: 2.4
Name: keithley-tempcontrol
Version: 2025.0.9
Summary: Keithley Temperature Control for CGSE
Author: IVS KU Leuven
Maintainer-email: Rik Huygen <rik.huygen@kuleuven.be>, Sara Regibo <sara.regibo@kuleuven.be>
License-Expression: MIT
Keywords: CGSE,Common-EGSE,hardware testing,software framework,temperature control
Requires-Python: >=3.9
Requires-Dist: cgse-common
Requires-Dist: cgse-gui
Requires-Dist: pyqt5>=5.15.11
Provides-Extra: test
Requires-Dist: pytest; extra == 'test'
Requires-Dist: pytest-cov; extra == 'test'
Requires-Dist: pytest-mock; extra == 'test'
